{
    "name": "Food",
    "description": "Delicious dishes and ingredients",
    "icon": "bi-cup-hot",
    "color": "danger",
    "words": [
        "PIZZA",
        "BURGER",
        "SALAD",
        "SUSHI",
        "PASTA",
        "STEAK",
        "CHICKEN",
        "FISH",
        "BREAD",
        "CHEESE",
        "SANDWICH",
        "TACO",
        "BURRITO",
        "ENCHILADA",
        "QUESADILLA",
        "NACHOS",
        "CHIPS",
        "DIP",
        "SOUP",
        "STEW",
        "CHILI",
        "CURRY",
        "RICE",
        "BEANS",
        "LENTILS",
        "QUINOA",
        "COUSCOUS",
        "BULGUR",
        "FARRO",
        "BARLEY",
        "OATS",
        "WHEAT",
        "CORN",
        "POTATO",
        "SWEET POTATO",
        "CARROT",
        "BROCCOLI",
        "CAULIFLOWER",
        "SPINACH",
        "KALE",
        "LETTUCE",
        "TOMATO",
        "ONION",
        "GARLIC",
        "GINGER",
        "PEPPER",
        "SALT",
        "SUGAR",
        "HONEY",
        "MAPLE SYRUP",
        "VINEGAR",
        "OIL",
        "BUTTER",
        "MARGARINE",
        "CREAM",
        "MILK",
        "YOGURT",
        "ICE CREAM",
        "CAKE",
        "COOKIE",
        "PIE",
        "BROWNIE",
        "MUFFIN",
        "CUPCAKE",
        "DONUT",
        "CROISSANT",
        "BAGEL",
        "TOAST",
        "PANCAKE",
        "WAFFLE",
        "FRENCH TOAST",
        "OMELET",
        "SCRAMBLED EGGS",
        "BACON",
        "SAUSAGE",
        "HAM",
        "TURKEY",
        "DUCK",
        "LAMB",
        "PORK",
        "VEAL",
        "VENISON",
        "BUFFALO",
        "BISON",
        "ELK",
        "MOOSE",
        "RABBIT",
        "QUAIL",
        "PHEASANT",
        "GOOSE",
        "SHRIMP",
        "CRAB",
        "LOBSTER",
        "CLAM",
        "OYSTER",
        "MUSSEL",
        "SCALLOP",
        "SALMON",
        "TROUT",
        "BASS",
        "PIKE",
        "PERCH",
        "CARP",
        "CATFISH",
        "TILAPIA",
        "MAHI MAHI",
        "TUNA",
        "MACKEREL",
        "SARDINE",
        "ANCHOVY",
        "HERRING",
        "COD",
        "HADDOCK",
        "POLLOCK",
        "WHITING",
        "FLOUNDER",
        "SOLE",
        "HALIBUT",
        "RED SNAPPER",
        "GROUPER",
        "SEA BASS",
        "ROCKFISH",
        "LINGCOD",
        "WOLF EEL",
        "MONKFISH",
        "SKATE",
        "STINGRAY",
        "SHARK",
        "SWORDFISH",
        "MARLIN",
        "SAILFISH",
        "BLUEFIN",
        "YELLOWFIN",
        "ALBACORE",
        "BONITO",
        "WAHOO",
        "DORADO",
        "ROOSTERFISH",
        "JACK",
        "POMPANO",
        "PERMIT",
        "TARPON",
        "BONEFISH",
        "TREVALLY",
        "COBIA",
        "AMBERJACK",
        "YELLOWTAIL",
        "HAMACHI",
        "KAMPACHI",
        "KANPACHI",
        "HIRAMASA",
        "BURI",
        "SAWARA",
        "SABA",
        "AJI",
        "SHIMA AJI",
        "KINMEDAI",
        "TAI",
        "MADAI",
        "KASUGO",
        "KURODAI",
        "AKAMUTSU",
        "HATA",
        "MUTSU",
        "KANPACHI",
        "HAMACHI",
        "BURI",
        "SAWARA",
        "SABA",
        "AJI",
        "SHIMA AJI",
        "KINMEDAI",
        "TAI",
        "MADAI",
        "KASUGO",
        "KURODAI",
        "AKAMUTSU",
        "HATA",
        "MUTSU"
    ]
}
